ThreeDViewer/__init__.py
ThreeDViewer/examples.py
ThreeDViewer/image.py
ThreeDViewer/vector.py
ThreeDViewer/data/__init__.py
ThreeDViewer/data/cylinder.ovf
threedviewer-0.2.1.dist-info/licenses/LICENSE.txt
threedviewer-0.2.1.dist-info/METADATA
threedviewer-0.2.1.dist-info/WHEEL
threedviewer-0.2.1.dist-info/top_level.txt
threedviewer-0.2.1.dist-info/RECORD
