Metadata-Version: 2.4
Name: ThreeDViewer
Version: 0.2.1
Summary: Tool for visualising 3D vector and scalar fields
Author: Andreas Apseros
License-Expression: BSD-3-Clause
Project-URL: Homepage, https://github.com/apseros/ThreeDViewer
Project-URL: Issues, https://github.com/apseros/ThreeDViewer/issues
Classifier: Programming Language :: Python :: 3
Classifier: Intended Audience :: Science/Research
Classifier: Operating System :: OS Independent
Requires-Python: >=3.9
License-File: LICENSE.txt
Requires-Dist: numpy
Requires-Dist: magpack
Requires-Dist: matplotlib
Provides-Extra: vtk
Requires-Dist: pyvisa; extra == "vtk"
Requires-Dist: scipy; extra == "vtk"
Dynamic: license-file
